package_monitor/__init__.py
package_monitor/app_settings.py
package_monitor/apps.py
package_monitor/auth_hooks.py
package_monitor/managers.py
package_monitor/models.py
package_monitor/tasks.py
package_monitor/urls.py
package_monitor/views.py
package_monitor/core/__init__.py
package_monitor/core/distribution_packages.py
package_monitor/core/metadata_helpers.py
package_monitor/core/pypi.py
package_monitor/core/schedule.py
package_monitor/locale/django.pot
package_monitor/locale/de/LC_MESSAGES/django.mo
package_monitor/locale/de/LC_MESSAGES/django.po
package_monitor/locale/en/LC_MESSAGES/django.mo
package_monitor/locale/en/LC_MESSAGES/django.po
package_monitor/locale/es/LC_MESSAGES/django.mo
package_monitor/locale/es/LC_MESSAGES/django.po
package_monitor/locale/fr_FR/LC_MESSAGES/django.mo
package_monitor/locale/fr_FR/LC_MESSAGES/django.po
package_monitor/locale/it_IT/LC_MESSAGES/django.mo
package_monitor/locale/it_IT/LC_MESSAGES/django.po
package_monitor/locale/ja/LC_MESSAGES/django.mo
package_monitor/locale/ja/LC_MESSAGES/django.po
package_monitor/locale/ko_KR/LC_MESSAGES/django.mo
package_monitor/locale/ko_KR/LC_MESSAGES/django.po
package_monitor/locale/ru/LC_MESSAGES/django.mo
package_monitor/locale/ru/LC_MESSAGES/django.po
package_monitor/locale/uk/LC_MESSAGES/django.mo
package_monitor/locale/uk/LC_MESSAGES/django.po
package_monitor/locale/zh_Hans/LC_MESSAGES/django.mo
package_monitor/locale/zh_Hans/LC_MESSAGES/django.po
package_monitor/management/commands/packagemonitorcli.py
package_monitor/migrations/0001_initial.py
package_monitor/migrations/0002_add_editable_and_refactor_json_fields.py
package_monitor/migrations/0003_add_update_notifications.py
package_monitor/migrations/__init__.py
package_monitor/static/package_monitor/css/global.css
package_monitor/static/package_monitor/css/package_list.css
package_monitor/static/package_monitor/images/Spinner-1s-64px-dark.gif
package_monitor/static/package_monitor/images/Spinner-1s-64px-light.gif
aa_package_monitor-2.2.2.dist-info/licenses/LICENSE
aa_package_monitor-2.2.2.dist-info/WHEEL
aa_package_monitor-2.2.2.dist-info/METADATA
aa_package_monitor-2.2.2.dist-info/RECORD
