Metadata-Version: 2.4
Name: aa-package-monitor
Version: 2.2.2
Summary: An app that helps keep track of installed packages
Author-email: Erik Kalkoken <kalkoken87@gmail.com>
Requires-Python: >=3.8
Classifier: Environment :: Web Environment
Classifier: Framework :: Django
Classifier: Framework :: Django :: 4.2
Classifier: Intended Audience :: End Users/Desktop
Classifier: License :: OSI Approved :: MIT License
Classifier: Operating System :: OS Independent
Classifier: Programming Language :: Python
Classifier: Programming Language :: Python :: 3.8
Classifier: Programming Language :: Python :: 3.9
Classifier: Programming Language :: Python :: 3.10
Classifier: Programming Language :: Python :: 3.11
Classifier: Programming Language :: Python :: 3.12
Classifier: Topic :: Internet :: WWW/HTTP
Classifier: Topic :: Internet :: WWW/HTTP :: Dynamic Content
License-File: LICENSE
Requires-Dist: allianceauth<5,>=4
Requires-Dist: allianceauth-app-utils>=1.17.1
Requires-Dist: importlib_metadata
Requires-Dist: aiohttp>=3.8
Requires-Dist: packaging>=22
Requires-Dist: recurrent>=0.4.1
Requires-Dist: python-dateutil>=2.9
Requires-Dist: PyYAML
Project-URL: Changelog, https://gitlab.com/ErikKalkoken/aa-package-monitor/-/blob/master/CHANGELOG.md
Project-URL: Homepage, https://gitlab.com/ErikKalkoken/aa-package-monitor
Project-URL: Source, https://gitlab.com/ErikKalkoken/aa-package-monitor
Project-URL: Tracker, https://gitlab.com/ErikKalkoken/aa-package-monitor/-/issues
